{
    "status": "ok",
    "totalResults": 70,
    "articles": [
        {
            "source": {
                "id": "the-verge",
                "name": "The Verge"
            },
            "author": "Tom Warren",
            "title": "Logitech's new G Pro X 2 gaming headset has graphene audio drivers - The Verge",
            "description": "Logitech’s new G Pro X 2 has lots of improvements over the original. It has graphene audio drivers, a lighter frame, much better battery life, and even rotatable ear cups.",
            "url": "https://www.theverge.com/2023/5/24/23733249/logitech-g-pro-x-2-gaming-headset-graphene-audio-drivers-release-date-pricing",
            "urlToImage": "https://cdn.vox-cdn.com/thumbor/tdSyFWnKArlhLQGgetnRT5gDUdo=/0x0:2640x1749/1200x628/filters:focal(1320x875:1321x876)/cdn.vox-cdn.com/uploads/chorus_asset/file/24675694/VLS_5011.jpg",
            "publishedAt": "2023-05-24T07:01:00Z",
            "content": "Logitechs new G Pro X 2 gaming headset has graphene audio drivers\r\nLogitechs new G Pro X 2 gaming headset has graphene audio drivers\r\n / The G Pro X 2 has a lot more battery life and is lighter than … [+4253 chars]"
        },
        {
            "source": {
                "id": "the-verge",
                "name": "The Verge"
            },
            "author": "Jess Weatherbed",
            "title": "The Logi Dock Flex is Logitech’s $699 solution for hot desking - The Verge",
            "description": "Logitech has announced the Logi Dock Flex, its latest all-in-one USB-C docking station designed to alleviate some of the frustrations of hot desking and hybrid working.",
            "url": "https://www.theverge.com/2023/5/24/23734946/logitech-logi-dock-flex-hot-desking-features-price",
            "urlToImage": "https://cdn.vox-cdn.com/thumbor/87sIYcLbPO26fPZscwaI3_LkYB4=/396x213:3619x2133/1200x628/filters:focal(2000x1125:2001x1126)/cdn.vox-cdn.com/uploads/chorus_asset/file/24676953/High_Resolution_PNG_Logi_Dock_Flex_ENVR_Join_Call.png",
            "publishedAt": "2023-05-24T07:01:00Z",
            "content": "Logitechs solution for hot desking is a $699 dock with a screen\r\nLogitechs solution for hot desking is a $699 dock with a screen\r\n / The Logi Dock Flex will be available sometime in fall 2023.\r\nByJes… [+2592 chars]"
        },
        {
            "source": {
                "id": null,
                "name": "ComicBook.com"
            },
            "author": "ComicBook.com",
            "title": "Viral Zelda: Tears of the Kingdom Ad Reportedly Inspired by A True Story - ComicBook.com",
            "description": "They have their hands full with their daughter Royce after welcoming their little one via surrogate last year",
            "url": "https://comicbook.com/gaming/news/the-legend-of-zelda-tears-of-the-kingdom-ad-true-story/",
            "urlToImage": "https://sm.ign.com/t/ign_za/feature/t/the-legend/the-legend-of-zelda-tears-of-the-kingdom-18-things-to-pay-at_4jv7.1200.jpg",
            "publishedAt": "2023-05-24T03:24:00Z",
            "content": null
        },
        {
            "source": {
                "id": null,
                "name": "Daily Mail"
            },
            "author": "Jade Watkins",
            "title": "Rebel Wilson shows off her weight loss in a sparkly green dress at Cannes with Ramona Agruma - Daily Mail",
            "description": "They have their hands full with their daughter Royce after welcoming their little one via surrogate last year.",
            "url": "https://www.dailymail.co.uk/tvshowbiz/article-12117863/Rebel-Wilson-shows-weight-loss-sparkly-green-dress-Cannes-Ramona-Agruma.html",
            "urlToImage": "https://i.dailymail.co.uk/1s/2023/05/24/03/71338593-0-image-a-17_1684895605975.jpg",
            "publishedAt": "2023-05-24T02:21:35Z",
            "content": "They have their hands full with their daughter Royce after welcoming their little one via surrogate last year.\r\nAnd Rebel Wilson, 43, and her fiancée Ramona Agruma enjoyed a well-deserved night off p… [+3741 chars]"
        },
        {
            "source": {
                "id": null,
                "name": "Fox Business"
            },
            "author": "Eric Revell",
            "title": "Microsoft announces Windows Copilot AI-powered assistant - Fox Business",
            "description": "Microsoft unveiled its new AI-powered assistant known as Windows Copilot, a chatbot which will work across apps on Windows 11 and is set for a June preview for users.",
            "url": "https://www.foxbusiness.com/technology/microsoft-announces-windows-copilot-ai-powered-assistant",
            "urlToImage": "https://a57.foxnews.com/static.foxbusiness.com/foxbusiness.com/content/uploads/2023/01/0/0/Microsoft-2-1.jpg?ve=1&tl=1",
            "publishedAt": "2023-05-24T02:02:31Z",
            "content": "Microsoft announced Tuesday it will bring its Windows Copilot, a chatbot powered by artificial intelligence (AI)\r\n, to the home screen of computers running Windows 11.\r\nWindows Copilot\r\n will serve a… [+3126 chars]"
        },
        {
            "source": {
                "id": null,
                "name": "YouTube"
            },
            "author": null,
            "title": "Warhammer 40000: Boltgun - Official Launch Trailer - IGN",
            "description": "Warhammer 40,000: Boltgun is available now on PlayStation 5, PlayStation 4, Xbox Series X/S, Xbox One, Nintendo Switch, and PC. Watch the action-packed, bloo...",
            "url": "https://www.youtube.com/watch?v=LrCErZCF7jY",
            "urlToImage": "https://i.ytimg.com/vi/LrCErZCF7jY/maxresdefault.jpg",
            "publishedAt": "2023-05-24T00:00:07Z",
            "content": null
        },
        {
            "source": {
                "id": null,
                "name": "GSMArena.com"
            },
            "author": "Vlad",
            "title": "Amazon's new Fire Max 11 tablet is its most powerful yet - GSMArena.com",
            "description": "It's available for pre-order today at $229. Today Amazon has unveiled its most powerful tablet ever, the Fire Max 11. As the name implies, this has an...",
            "url": "https://www.gsmarena.com/amazons_new_fire_max_11_tablet_is_its_most_powerful_yet-news-58652.php",
            "urlToImage": "https://fdn.gsmarena.com/imgroot/news/23/05/amazon-fire-max-11/-952x498w6/gsmarena_000.jpg",
            "publishedAt": "2023-05-23T23:59:01Z",
            "content": "Today Amazon has unveiled its most powerful tablet ever, the Fire Max 11. As the name implies, this has an 11-inch touchscreen with 2000x1200 resolution.\r\nAt the helm sits \"a powerful octa-core proce… [+1171 chars]"
        },
        {
            "source": {
                "id": null,
                "name": "Kotaku"
            },
            "author": "Luke Plunkett",
            "title": "New Total War Game Has Been Announced, Set In Ancient Egypt - Kotaku",
            "description": "We just had a Warhammer one, so now it's time to go back to the history books",
            "url": "https://kotaku.com/total-war-pharaoh-sega-creative-assembly-announced-new-1850467750",
            "urlToImage": "https://i.kinja-img.com/gawker-media/image/upload/c_fill,f_auto,fl_progressive,g_center,h_675,pg_1,q_80,w_1200/7f414ebfaa86cf34d0946d36b10ecf1f.jpg",
            "publishedAt": "2023-05-23T23:30:00Z",
            "content": "After wrapping up their Warhammer trilogy in the most blockbuster way possible, Creative Assembly have just announced a brand new Total War game based on the stuff the series made its name on: actual… [+2493 chars]"
        },
        {
            "source": {
                "id": null,
                "name": "YouTube"
            },
            "author": null,
            "title": "Remnant 2 - Official Challenger Archetype Reveal Trailer - IGN",
            "description": "Remnant 2 is an upcoming action-survival shooter with a new trailer that shows off the Challenger Archetype, giving players the chance to excel in their up-c...",
            "url": "https://www.youtube.com/watch?v=Wy0X0PnkpQg",
            "urlToImage": "https://i.ytimg.com/vi/Wy0X0PnkpQg/maxresdefault.jpg",
            "publishedAt": "2023-05-23T23:00:24Z",
            "content": null
        },
        {
            "source": {
                "id": null,
                "name": "Gameinformer.com"
            },
            "author": "Marcus Stewart",
            "title": "Mortal Kombat 1 Gameplay Will Premiere During Summer Game Fest - Game Informer",
            "description": "That's one big world premire for Summer Game Fest.",
            "url": "https://www.gameinformer.com/2023/05/23/mortal-kombat-1-gameplay-will-premiere-during-summer-game-fest",
            "urlToImage": "https://www.gameinformer.com/sites/default/files/styles/thumbnail/public/2023/05/23/87871443/mortal_kombat_1_trailer_mileena.jpg",
            "publishedAt": "2023-05-23T22:35:00Z",
            "content": "Mortal Kombat 1s incredible cinematic debut trailer ignited the collective excitement of a fanbase champing at the bit to see it in action. Looks like they'll only have to wait a couple more weeks. \r… [+983 chars]"
        },
        {
            "source": {
                "id": null,
                "name": "CNBC"
            },
            "author": "Julie Coleman",
            "title": "Apple's Eddy Cue says success starts by saying 'no' to almost everything - CNBC",
            "description": "Apple's Eddy Cue sat down for an exclusive interview with CNBC's Jim Cramer at the inaugural CNBC CEO Council Summit in Santa Barbara, California.",
            "url": "https://www.cnbc.com/2023/05/23/apples-eddy-cue-says-success-starts-by-saying-no-to-almost-everything.html",
            "urlToImage": "https://image.cnbcfm.com/api/v1/image/105060036-GettyImages-931009486.jpg?v=1684880419&w=1920&h=1080",
            "publishedAt": "2023-05-23T22:20:19Z",
            "content": "Apple's senior vice president of services Eddy Cue attributes a lot of the success the market's biggest company has to saying \"no\" more often than \"yes.\"\r\n\"We say 'no' to almost everything,\" Cue said… [+1149 chars]"
        },
        {
            "source": {
                "id": null,
                "name": "Kotaku"
            },
            "author": "Alyssa Mercante",
            "title": "Destiny 2 Gets PlayStation-Inspired Armor Sets And Cosmetics - Kotaku",
            "description": "The crossover includes cosmetics based on The Last of Us, Horizon Forbidden West, and God of War",
            "url": "https://kotaku.com/destiny-2-playstation-collab-season-of-the-deep-store-1850467565",
            "urlToImage": "https://i.kinja-img.com/gawker-media/image/upload/c_fill,f_auto,fl_progressive,g_center,h_675,pg_1,q_80,w_1200/80e42bedd9ba16328a768f21cf77919f.jpg",
            "publishedAt": "2023-05-23T22:20:00Z",
            "content": "Bungie has just revealed details for the upcoming Destiny 2 Season of the Deep, which includes a ton of new in-game events, fishing (yes, youll be able to fish in Destiny 2), and a PlayStation crosso… [+2145 chars]"
        },
        {
            "source": {
                "id": null,
                "name": "MacRumors"
            },
            "author": "Joe Rossignol",
            "title": "2023 Apple Design Award Finalists Revealed Ahead of WWDC - MacRumors",
            "description": "Ahead of WWDC 2023 next month, the finalists for this year's Apple Design Awards have been revealed online. Apple says the awards \"recognize...",
            "url": "https://www.macrumors.com/2023/05/23/2023-apple-design-award-finalists/",
            "urlToImage": "https://images.macrumors.com/t/iFBDo8ItGFus_WugSoMSW7A6NlI=/1600x/article-new/2023/05/Apple-Design-Award-Cube.jpeg",
            "publishedAt": "2023-05-23T22:12:13Z",
            "content": "Ahead of WWDC 2023 next month, the finalists for this year's Apple Design Awards have been revealed online. Apple says the awards \"recognize and celebrate the art, craft, creativity, and technical ex… [+773 chars]"
        },
        {
            "source": {
                "id": null,
                "name": "BleepingComputer"
            },
            "author": "Lawrence Abrams",
            "title": "Windows 11 getting native support for 7-Zip, RAR, and GZ archives - BleepingComputer",
            "description": "Microsoft is adding native support for RAR, 7-Zip, and GZ archives to an upcoming version of Windows 11 expected this week.",
            "url": "https://www.bleepingcomputer.com/news/microsoft/windows-11-getting-native-support-for-7-zip-rar-and-gz-archives/",
            "urlToImage": "https://www.bleepstatic.com/content/hl-images/2023/02/13/Windows_11_dark_hdr.jpg",
            "publishedAt": "2023-05-23T21:46:08Z",
            "content": "Microsoft is adding native support for RAR, 7-Zip, and GZ archives to an upcoming version of Windows 11 expected this week.\r\nToday, Microsoft announced a flurry of news at the Build 2023 conference, … [+1898 chars]"
        },
        {
            "source": {
                "id": "the-verge",
                "name": "The Verge"
            },
            "author": "Allison Johnson",
            "title": "Photoshop’s Generative Fill tool turns vacation photos into nightmares - The Verge",
            "description": "Photoshop’s new Generative Fill tool uses AI to add and remove elements from your photos. It’s an impressive tool for edits... and can also make the stuff of nightmares.",
            "url": "https://www.theverge.com/2023/5/23/23734821/photoshop-generative-ai-fill-tool-adobe",
            "urlToImage": "https://cdn.vox-cdn.com/thumbor/xz_xfCp_Cy3E0IOGhjT5rb4bYPU=/0x0:4080x3060/1200x628/filters:focal(2040x1530:2041x1531)/cdn.vox-cdn.com/uploads/chorus_asset/file/24676983/IMG_20230323_133713_volcano.jpg",
            "publishedAt": "2023-05-23T21:30:00Z",
            "content": "Photoshops generative AI tool turned my vacation photos into nightmare fuel\r\nPhotoshops generative AI tool turned my vacation photos into nightmare fuel\r\n / The new generative AI tool looks like an i… [+3322 chars]"
        },
        {
            "source": {
                "id": null,
                "name": "Android Police"
            },
            "author": "Louis Pavlakos",
            "title": "The solution to Pixel fingerprint scanner problems may be right under your nose - Android Police",
            "description": "No, it's not a software update",
            "url": "https://www.androidpolice.com/google-pixel-fingerprint-scanner-problems-workaround/",
            "urlToImage": "https://static1.anpoimages.com/wordpress/wp-content/uploads/2022/10/google-pixel-7-review-14.jpg",
            "publishedAt": "2023-05-23T21:25:00Z",
            "content": "For as useful as in-screen fingerprint scanners are, sometimes they'll just flat-out refuse to authenticate you. While some devices, like recent models in the Galaxy S lineup, use more secure and fas… [+1664 chars]"
        },
        {
            "source": {
                "id": "the-verge",
                "name": "The Verge"
            },
            "author": "Umar Shakir",
            "title": "HP printers are getting the blue screen of death - The Verge",
            "description": "Some HP OfficeJet 9020e and 8010e series printers are getting bricked and left with a BSOD and error code 83C0000B. HP had released a faulty firmware that is affecting printers worldwide, and it has yet to resolve it.",
            "url": "https://www.theverge.com/2023/5/23/23734185/hp-officejet-blue-screen-error-83c0000b-bricked",
            "urlToImage": "https://cdn.vox-cdn.com/thumbor/CIYug3upnOx-fcjfZlq16j25MZI=/0x0:3833x2555/1200x628/filters:focal(1917x1278:1918x1279)/cdn.vox-cdn.com/uploads/chorus_asset/file/24676377/Screenshot_2023_05_23_at_12.45.22_PM.jpeg",
            "publishedAt": "2023-05-23T21:14:45Z",
            "content": "Some HP printers are getting a blue screen error and being rendered unusable\r\nSome HP printers are getting a blue screen error and being rendered unusable\r\n / HP has been scrambling for days to fix a… [+2790 chars]"
        },
        {
            "source": {
                "id": null,
                "name": "Android Police"
            },
            "author": "Louis Pavlakos",
            "title": "Google Bard gets visual as it learns to respond with images - Android Police",
            "description": "Giving you a better idea of what you're searching for",
            "url": "https://www.androidpolice.com/google-bard-image-responses/",
            "urlToImage": "https://static1.anpoimages.com/wordpress/wp-content/uploads/2023/04/google-bard-ap-hero.jpg",
            "publishedAt": "2023-05-23T21:10:00Z",
            "content": "A few weeks ago, Google announced at I/O that Bard would be getting a host of new features in the coming weeks. Some, like exports and dark mode, have already begun rolling out, but others have taken… [+1541 chars]"
        },
        {
            "source": {
                "id": null,
                "name": "AppleInsider"
            },
            "author": "Evan Selleck",
            "title": "Samsung's new 27-inch monitor competes with Apple's Studio Display at half the price - AppleInsider",
            "description": "Samsung on Tuesday officially unveiled the newest smart monitors in its M-series lineup, with a $649 27-inch Studio Display competitor joining the mix.",
            "url": "https://appleinsider.com/articles/23/05/23/samsungs-new-27-inch-monitor-competes-with-apples-studio-display-at-half-the-price",
            "urlToImage": "https://photos5.appleinsider.com/gallery/54567-110318-Samsung-M-smart-monitor-xl.jpg",
            "publishedAt": "2023-05-23T21:07:56Z",
            "content": "Samsung's new M8 Smart Monitor\r\nSamsung on Tuesday officially unveiled the newest smart monitors in its M-series lineup, with a $649 27-inch Studio Display competitor joining the mix.\r\nAnnounced at C… [+3131 chars]"
        },
        {
            "source": {
                "id": null,
                "name": "YouTube"
            },
            "author": null,
            "title": "Tear-Down Speedrun of NVIDIA RTX 4060 Ti Founders Edition - Gamers Nexus",
            "description": "Sponsor: Get 10% off Squarespace purchases (https://geni.us/BqEpf)We already reviewed and benchmarked the NVIDIA RTX 4060 Ti Founders Edition GPU -- and it d...",
            "url": "https://www.youtube.com/watch?v=pKbpsphNVUI",
            "urlToImage": "https://i.ytimg.com/vi/pKbpsphNVUI/maxresdefault.jpg",
            "publishedAt": "2023-05-23T21:00:32Z",
            "content": null
        }
    ]
}